Workbook

Sheet Recon Summary
A1: Reconciliation Summary
A2: High-level summary, netting bridges, and netting view. All formulas reference 'Recon - Stripe vs Internal (B)'.
A4: NETTING BRIDGES — refs that pair off
A6: Dispute composite (5.1 = 1.4 + 2.2)
A7: Ref | B7: rc | C7: Component | D7: Amount
A8: 1.4 | B8: dispute_gross | C8: Internal split (gross) | D8: ='Recon - Stripe vs Internal'!R8 -> -603068.1
A9: 2.2 | B9: dispute_fee | C9: Internal split (fee) | D9: ='Recon - Stripe vs Internal'!R11 -> -54135
A10: Sum | C10: 1.4 + 2.2 (Internal) | D10: =D8+D9 -> -657203.1
A11: 5.1 | B11: dispute | C11: Stripe NET (composite) | D11: ='Recon - Stripe vs Internal'!S20 -> -657203.1
A12: Δ | C12: Sum − Stripe NET | D12: =D10-D11 -> 0 | E12: =IF(ABS(D12)<1,"✓ ties","✗") -> ✓ ties
A14: Dispute reversal composite (5.2 = 1.5 + 2.3)
A15: Ref | B15: rc | C15: Component | D15: Amount
A16: 1.5 | B16: dispute_reversal_gross | C16: Internal split (gross) | D16: ='Recon - Stripe vs Internal'!R9 -> 176609.97
A17: 2.3 | B17: dispute_reversal_fee | C17: Internal split (fee) | D17: ='Recon - Stripe vs Internal'!R12 -> 450
A18: Sum | C18: 1.5 + 2.3 (Internal) | D18: =D16+D17 -> 177059.97
A19: 5.2 | B19: dispute_reversal | C19: Stripe NET (composite) | D19: ='Recon - Stripe vs Internal'!S21 -> 177059.97
A20: Δ | C20: Sum − Stripe NET | D20: =D18-D19 -> 0 | E20: =IF(ABS(D20)<1,"✓ ties","✗") -> ✓ ties
A22: Reserve mechanic pair (7.1 + 7.2 = 0)
A23: Ref | B23: rc | C23: Component | D23: Amount
A24: 7.1 | B24: payout_min_balance_hold | C24: Stripe (held) | D24: ='Recon - Stripe vs Internal'!S23 -> -5280000
A25: 7.2 | B25: payout_min_balance_release | C25: Stripe (released) | D25: ='Recon - Stripe vs Internal'!S24 -> 5280000
A26: Sum | C26: 7.1 + 7.2 | D26: =D24+D25 -> 0 | E26: =IF(ABS(D26)<1,"✓ nets to zero","✗") -> ✓ nets to zero
A29: HIGH-LEVEL SUMMARY — Total by source flag
A31: Source | B31: Description | C31: Internal Total | D31: Stripe NET Total | E31: Net Variance | F31: Notes
A32: B | B32: Both Stripe & Internal (refs 1.1, 1.2, 1.3, 1.6, 2.5, 3.1, 3.2, 3.3, 4.1, 4.2, 4.3) | C32: ='Recon - Stripe vs Internal'!R5+'Recon - Stripe vs Internal'!R6+'Recon - Stripe vs Internal'!R7+'Recon - Stripe vs Internal'!R10+'Recon - Stripe vs Internal'!R13+'Recon - Stripe vs Internal'!R14+'Recon - Stripe vs Internal'!R15+'Recon - Stripe vs Internal'!R16+'Recon - Stripe vs Internal'!R17+'Recon - Stripe vs Internal'!R18+'Recon - Stripe vs Internal'!R19 -> 24568257 | D32: ='Recon - Stripe vs Internal'!S5+'Recon - Stripe vs Internal'!S6+'Recon - Stripe vs Internal'!S7+'Recon - Stripe vs Internal'!S10+'Recon - Stripe vs Internal'!S13+'Recon - Stripe vs Internal'!S14+'Recon - Stripe vs Internal'!S15+'Recon - Stripe vs Internal'!S16+'Recon - Stripe vs Internal'!S17+'Recon - Stripe vs Internal'!S18+'Recon - Stripe vs Internal'!S19 -> 23856290 | E32: =C32-D32 -> 711967.64 | F32: Should tie except SIGN ANOMALY on ref 2.5 fee + revenue_share now Stripe-only (raw data)
A33: S | B33: Stripe only — composites + true Stripe-only (refs 5.1, 5.2, 6.1, 7.1, 7.2) | C33: ='Recon - Stripe vs Internal'!R20+'Recon - Stripe vs Internal'!R21+'Recon - Stripe vs Internal'!R22+'Recon - Stripe vs Internal'!R23+'Recon - Stripe vs Internal'!R24 -> 0 | D33: ='Recon - Stripe vs Internal'!S20+'Recon - Stripe vs Internal'!S21+'Recon - Stripe vs Internal'!S22+'Recon - Stripe vs Internal'!S23+'Recon - Stripe vs Internal'!S24 -> -454223.13 | E33: =C33-D33 -> 454223.13 | F33: Composites 5.1+5.2 net off with Internal splits. Reserves 7.1+7.2=0. True Stripe-only: 6.1 other_adjustment $25,920.
A34: I | B34: Internal only — splits + true Internal-only (refs 1.4, 1.5, 2.2, 2.3, 8.1) | C34: ='Recon - Stripe vs Internal'!R8+'Recon - Stripe vs Internal'!R9+'Recon - Stripe vs Internal'!R11+'Recon - Stripe vs Internal'!R12+'Recon - Stripe vs Internal'!R25 -> 178379.73 | D34: ='Recon - Stripe vs Internal'!S8+'Recon - Stripe vs Internal'!S9+'Recon - Stripe vs Internal'!S11+'Recon - Stripe vs Internal'!S12+'Recon - Stripe vs Internal'!S25 -> 0 | E34: =C34-D34 -> 178379.73 | F34: Splits 1.4+2.2 net to 5.1 (Stripe). Splits 1.5+2.3 net to 5.2. True Internal-only: 8.1 subscription_tax $658,523.
A35: TOTAL | C35: =C32+C33+C34 -> 24746637 | D35: =D32+D33+D34 -> 23402066 | E35: =C35-D35 -> 1344570.5
A38: NETTING VIEW — Internal − Stripe NET (signed). SUM gives true residual.
A40: Item | B40: Refs | C40: Sign | D40: Internal − Stripe | E40: Notes
A41: Tied B-flag rows (excl. 2.5 fee, excl. 4.3 revenue_share) | B41: 1.1, 1.2, 1.3, 1.6, 3.1, 3.2, 3.3, 4.1, 4.2 | C41: + | D41: =('Recon - Stripe vs Internal'!R5+'Recon - Stripe vs Internal'!R6+'Recon - Stripe vs Internal'!R7+'Recon - Stripe vs Internal'!R10+'Recon - Stripe vs Internal'!R14+'Recon - Stripe vs Internal'!R15+'Recon - Stripe vs Internal'!R16+'Recon - Stripe vs Internal'!R17+'Recon - Stripe vs Internal'!R18)-('Recon - Stripe vs Internal'!S5+'Recon - Stripe vs Internal'!S6+'Recon - Stripe vs Internal'!S7+'Recon - Stripe vs Internal'!S10+'Recon - Stripe vs Internal'!S14+'Recon - Stripe vs Internal'!S15+'Recon - Stripe vs Internal'!S16+'Recon - Stripe vs Internal'!S17+'Recon - Stripe vs Internal'!S18) -> 576335.9 | E41: Includes the +$576,336 charge-side mirror of the fee sign anomaly. Will tie to 0 once sign on Data-Internal!D7 is corrected.
A42: Sign anomaly on fee (ref 2.5) | B42: 2.5 | C42: + | D42: ='Recon - Stripe vs Internal'!R13-'Recon - Stripe vs Internal'!S13 -> 576119.07 | E42: +$576,119 — billing/fee recorded as positive when it should be negative.
A43: Dispute composite netting | B43: 1.4 + 2.2 vs 5.1 | C43: + | D43: =('Recon - Stripe vs Internal'!R8+'Recon - Stripe vs Internal'!R11)-'Recon - Stripe vs Internal'!S20 -> 0 | E43: Should be 0 — Internal splits sum to Stripe composite NET.
A44: Dispute reversal composite netting | B44: 1.5 + 2.3 vs 5.2 | C44: + | D44: =('Recon - Stripe vs Internal'!R9+'Recon - Stripe vs Internal'!R12)-'Recon - Stripe vs Internal'!S21 -> 0 | E44: Should be 0 — Internal splits sum to Stripe composite NET.
A45: Reserve mechanic netting | B45: 7.1 + 7.2 | C45: + | D45: =('Recon - Stripe vs Internal'!R23+'Recon - Stripe vs Internal'!R24)-('Recon - Stripe vs Internal'!S23+'Recon - Stripe vs Internal'!S24) -> 0 | E45: Reserves net to 0 across the pair. Internal=0, Stripe=0, so Δ=0.
A46: Stripe-only adjustment (ref 6.1) | B46: 6.1 | C46: + | D46: ='Recon - Stripe vs Internal'!R22-'Recon - Stripe vs Internal'!S22 -> -25920 | E46: Internal $0 − Stripe $25,920 = −$25,920. True Stripe-only line.
A47: Stripe-only revenue_share (ref 4.3) | B47: 4.3 | C47: + | D47: ='Recon - Stripe vs Internal'!R19-'Recon - Stripe vs Internal'!S19 -> -440487.33 | E47: Internal $0 − Stripe $440,487 = −$440,487. Missing from Internal raw extract.
A48: Internal-only tax (ref 8.1) | B48: 8.1 | C48: + | D48: ='Recon - Stripe vs Internal'!R25-'Recon - Stripe vs Internal'!S25 -> 658522.86 | E48: Internal $658,523 − Stripe $0 = +$658,523. True Internal-only — booked separately to 2300.
A50: Net residual (SUM of signed amounts above) | C50: = | D50: =SUM(D41:D48) -> 1344570.5
A51: Cross-check: grand total Internal − Stripe (from summary above) | D51: =C35-D35 -> 1344570.5 | E51: Should equal D50 — proves netting view captures the full residual.

Sheet Recon - Stripe vs Internal
A1: Stripe ↔ Internal Reconciliation — grouped by Type
A2: Rows grouped by economic Type. Source flag: B=Both, S=Stripe only, I=Internal only. Internal cells = SUMIFS(Data-Internal, cat, rc). Stripe NET = col F (gross+fee).
A4: Type | B4: reporting_category | C4: Src | D4: Ref | E4: Description | F4: billing | G4: billing_instant | H4: client_invoice | I4: cx_transfer | J4: in_app | K4: other | L4: payroll | M4: connect | N4: subscription_silver | O4: subscription_diamond | P4: subscription_lite_and_cobranded | Q4: subscription_tax | R4: Internal Total | S4: Stripe NET | T4: Variance | U4: Tie? | V4: Exception Type | W4: Comments / nets off with
A5: Gross activity | B5: charge | C5: B | D5: 1.1 | E5: ='Data - Stripe'!H4 -> 0 | F5: =SUMIFS('Data - Internal'!$D$2:$D$91,'Data - Internal'!$A$2:$A$91,F$4,'Data - Internal'!$B$2:$B$91,$B5) -> 17389232 | G5: =SUMIFS('Data - Internal'!$D$2:$D$91,'Data - Internal'!$A$2:$A$91,G$4,'Data - Internal'!$B$2:$B$91,$B5) -> 0 | H5: =SUMIFS('Data - Internal'!$D$2:$D$91,'Data - Internal'!$A$2:$A$91,H$4,'Data - Internal'!$B$2:$B$91,$B5) -> 8444835.2 | I5: =SUMIFS('Data - Internal'!$D$2:$D$91,'Data - Internal'!$A$2:$A$91,I$4,'Data - Internal'!$B$2:$B$91,$B5) -> 0 | J5: =SUMIFS('Data - Internal'!$D$2:$D$91,'Data - Internal'!$A$2:$A$91,J$4,'Data - Internal'!$B$2:$B$91,$B5) -> 111736.11 | K5: =SUMIFS('Data - Internal'!$D$2:$D$91,'Data - Internal'!$A$2:$A$91,K$4,'Data - Internal'!$B$2:$B$91,$B5) -> 0 | L5: =SUMIFS('Data - Internal'!$D$2:$D$91,'Data - Internal'!$A$2:$A$91,L$4,'Data - Internal'!$B$2:$B$91,$B5) -> 133742.43 | M5: =SUMIFS('Data - Internal'!$D$2:$D$91,'Data - Internal'!$A$2:$A$91,M$4,'Data - Internal'!$B$2:$B$91,$B5) -> 9.1361091e+08 | ... Q5: =SUMIFS('Data - Internal'!$D$2:$D$91,'Data - Internal'!$A$2:$A$91,Q$4,'Data - Internal'!$B$2:$B$91,$B5) -> 0 | R5: =SUM(F5:Q5) -> 9.5412485e+08 | S5: =SUMIFS('Data - Stripe'!F:F,'Data - Stripe'!A:A,'Recon - Stripe vs Internal'!B5) -> 9.5354851e+08 | T5: =R5-S5 -> 576336.36 | U5: =IF(ABS(T5)<1,"✓","✗") -> ✗ | V5: SIGN ANOMALY (mirror of ref 2.5) | W5: Charge gross. Internal $954.1M = Stripe gross D4 ($954.1M). Stripe NET (col F) = gross + fee, so the $576K Δ vs NET nets off with ref 2.1 charge_fee.
A6: Gross activity | B6: refund | C6: B | D6: 1.2 | E6: ='Data - Stripe'!H5 -> 0 | F6: =SUMIFS('Data - Internal'!$D$2:$D$91,'Data - Internal'!$A$2:$A$91,F$4,'Data - Internal'!$B$2:$B$91,$B6) -> -111768.15 | G6: =SUMIFS('Data - Internal'!$D$2:$D$91,'Data - Internal'!$A$2:$A$91,G$4,'Data - Internal'!$B$2:$B$91,$B6) -> 0 | H6: =SUMIFS('Data - Internal'!$D$2:$D$91,'Data - Internal'!$A$2:$A$91,H$4,'Data - Internal'!$B$2:$B$91,$B6) -> -66831.18 | I6: =SUMIFS('Data - Internal'!$D$2:$D$91,'Data - Internal'!$A$2:$A$91,I$4,'Data - Internal'!$B$2:$B$91,$B6) -> 0 | J6: =SUMIFS('Data - Internal'!$D$2:$D$91,'Data - Internal'!$A$2:$A$91,J$4,'Data - Internal'!$B$2:$B$91,$B6) -> -143.88 | K6: =SUMIFS('Data - Internal'!$D$2:$D$91,'Data - Internal'!$A$2:$A$91,K$4,'Data - Internal'!$B$2:$B$91,$B6) -> 0 | L6: =SUMIFS('Data - Internal'!$D$2:$D$91,'Data - Internal'!$A$2:$A$91,L$4,'Data - Internal'!$B$2:$B$91,$B6) -> -1926 | M6: =SUMIFS('Data - Internal'!$D$2:$D$91,'Data - Internal'!$A$2:$A$91,M$4,'Data - Internal'!$B$2:$B$91,$B6) -> -3630794.7 | ... Q6: =SUMIFS('Data - Internal'!$D$2:$D$91,'Data - Internal'!$A$2:$A$91,Q$4,'Data - Internal'!$B$2:$B$91,$B6) -> 0 | R6: =SUM(F6:Q6) -> -4065765.5 | S6: =SUMIFS('Data - Stripe'!F:F,'Data - Stripe'!A:A,'Recon - Stripe vs Internal'!B6) -> -4065765.5 | T6: =R6-S6 -> 0 | U6: =IF(ABS(T6)<1,"✓","✗") -> ✓ | V6: =IF(U6="✓","",IF(R6=0,"Not in Internal",IF(S6=0,"Not in Stripe",IF(ABS(T6)<ABS(S6)*0.001,"Rounding",IF(T6>0,"Internal over Stripe","Internal under Stripe")))))
A7: Gross activity | B7: refund_failure | C7: B | D7: 1.3 | E7: ='Data - Stripe'!H6 -> 0 | F7: =SUMIFS('Data - Internal'!$D$2:$D$91,'Data - Internal'!$A$2:$A$91,F$4,'Data - Internal'!$B$2:$B$91,$B7) -> 0 | G7: =SUMIFS('Data - Internal'!$D$2:$D$91,'Data - Internal'!$A$2:$A$91,G$4,'Data - Internal'!$B$2:$B$91,$B7) -> 0 | H7: =SUMIFS('Data - Internal'!$D$2:$D$91,'Data - Internal'!$A$2:$A$91,H$4,'Data - Internal'!$B$2:$B$91,$B7) -> 0 | I7: =SUMIFS('Data - Internal'!$D$2:$D$91,'Data - Internal'!$A$2:$A$91,I$4,'Data - Internal'!$B$2:$B$91,$B7) -> 0 | J7: =SUMIFS('Data - Internal'!$D$2:$D$91,'Data - Internal'!$A$2:$A$91,J$4,'Data - Internal'!$B$2:$B$91,$B7) -> 0 | K7: =SUMIFS('Data - Internal'!$D$2:$D$91,'Data - Internal'!$A$2:$A$91,K$4,'Data - Internal'!$B$2:$B$91,$B7) -> 7302.96 | L7: =SUMIFS('Data - Internal'!$D$2:$D$91,'Data - Internal'!$A$2:$A$91,L$4,'Data - Internal'!$B$2:$B$91,$B7) -> 0 | M7: =SUMIFS('Data - Internal'!$D$2:$D$91,'Data - Internal'!$A$2:$A$91,M$4,'Data - Internal'!$B$2:$B$91,$B7) -> 0 | ... Q7: =SUMIFS('Data - Internal'!$D$2:$D$91,'Data - Internal'!$A$2:$A$91,Q$4,'Data - Internal'!$B$2:$B$91,$B7) -> 0 | R7: =SUM(F7:Q7) -> 7302.96 | S7: =SUMIFS('Data - Stripe'!F:F,'Data - Stripe'!A:A,'Recon - Stripe vs Internal'!B7) -> 7302.96 | T7: =R7-S7 -> 0 | U7: =IF(ABS(T7)<1,"✓","✗") -> ✓ | V7: =IF(U7="✓","",IF(R7=0,"Not in Internal",IF(S7=0,"Not in Stripe",IF(ABS(T7)<ABS(S7)*0.001,"Rounding",IF(T7>0,"Internal over Stripe","Internal under Stripe")))))
A8: Gross activity | B8: dispute_gross | C8: I | D8: 1.4 | E8: Gross principal of disputes/chargebacks (Internal split — Stripe nets into 'dispute' rc). | F8: =SUMIFS('Data - Internal'!$D$2:$D$91,'Data - Internal'!$A$2:$A$91,F$4,'Data - Internal'!$B$2:$B$91,$B8) -> -73224.81 | G8: =SUMIFS('Data - Internal'!$D$2:$D$91,'Data - Internal'!$A$2:$A$91,G$4,'Data - Internal'!$B$2:$B$91,$B8) -> 0 | H8: =SUMIFS('Data - Internal'!$D$2:$D$91,'Data - Internal'!$A$2:$A$91,H$4,'Data - Internal'!$B$2:$B$91,$B8) -> -29128.83 | I8: =SUMIFS('Data - Internal'!$D$2:$D$91,'Data - Internal'!$A$2:$A$91,I$4,'Data - Internal'!$B$2:$B$91,$B8) -> 0 | J8: =SUMIFS('Data - Internal'!$D$2:$D$91,'Data - Internal'!$A$2:$A$91,J$4,'Data - Internal'!$B$2:$B$91,$B8) -> 0 | K8: =SUMIFS('Data - Internal'!$D$2:$D$91,'Data - Internal'!$A$2:$A$91,K$4,'Data - Internal'!$B$2:$B$91,$B8) -> 0 | L8: =SUMIFS('Data - Internal'!$D$2:$D$91,'Data - Internal'!$A$2:$A$91,L$4,'Data - Internal'!$B$2:$B$91,$B8) -> 0 | M8: =SUMIFS('Data - Internal'!$D$2:$D$91,'Data - Internal'!$A$2:$A$91,M$4,'Data - Internal'!$B$2:$B$91,$B8) -> -455022.99 | ... Q8: =SUMIFS('Data - Internal'!$D$2:$D$91,'Data - Internal'!$A$2:$A$91,Q$4,'Data - Internal'!$B$2:$B$91,$B8) -> 0 | R8: =SUM(F8:Q8) -> -603068.1 | S8: =SUMIFS('Data - Stripe'!F:F,'Data - Stripe'!A:A,'Recon - Stripe vs Internal'!B8) -> 0 | T8: =R8-S8 -> -603068.1 | U8: =IF(ABS(T8)<1,"✓","✗") -> ✗ | V8: Bundled in Stripe ref 5.1 (composite) | W8: Internal-only split. Nets off with ref 5.1 dispute (Stripe composite). 1.4 + 2.2 = 5.1 NET (gross + fee).
A9: Gross activity | B9: dispute_reversal_gross | C9: I | D9: 1.5 | E9: Gross principal of dispute reversals (Internal split — Stripe nets into 'dispute_reversal' rc). | F9: =SUMIFS('Data - Internal'!$D$2:$D$91,'Data - Internal'!$A$2:$A$91,F$4,'Data - Internal'!$B$2:$B$91,$B9) -> 54531.63 | G9: =SUMIFS('Data - Internal'!$D$2:$D$91,'Data - Internal'!$A$2:$A$91,G$4,'Data - Internal'!$B$2:$B$91,$B9) -> 0 | H9: =SUMIFS('Data - Internal'!$D$2:$D$91,'Data - Internal'!$A$2:$A$91,H$4,'Data - Internal'!$B$2:$B$91,$B9) -> 7460.19 | I9: =SUMIFS('Data - Internal'!$D$2:$D$91,'Data - Internal'!$A$2:$A$91,I$4,'Data - Internal'!$B$2:$B$91,$B9) -> 0 | J9: =SUMIFS('Data - Internal'!$D$2:$D$91,'Data - Internal'!$A$2:$A$91,J$4,'Data - Internal'!$B$2:$B$91,$B9) -> 0 | K9: =SUMIFS('Data - Internal'!$D$2:$D$91,'Data - Internal'!$A$2:$A$91,K$4,'Data - Internal'!$B$2:$B$91,$B9) -> 0 | L9: =SUMIFS('Data - Internal'!$D$2:$D$91,'Data - Internal'!$A$2:$A$91,L$4,'Data - Internal'!$B$2:$B$91,$B9) -> 0 | M9: =SUMIFS('Data - Internal'!$D$2:$D$91,'Data - Internal'!$A$2:$A$91,M$4,'Data - Internal'!$B$2:$B$91,$B9) -> 111510.03 | ... Q9: =SUMIFS('Data - Internal'!$D$2:$D$91,'Data - Internal'!$A$2:$A$91,Q$4,'Data - Internal'!$B$2:$B$91,$B9) -> 0 | R9: =SUM(F9:Q9) -> 176609.97 | S9: =SUMIFS('Data - Stripe'!F:F,'Data - Stripe'!A:A,'Recon - Stripe vs Internal'!B9) -> 0 | T9: =R9-S9 -> 176609.97 | U9: =IF(ABS(T9)<1,"✓","✗") -> ✗ | V9: Bundled in Stripe ref 5.2 (composite) | W9: Internal-only split. Nets off with ref 5.2 dispute_reversal (Stripe composite). 1.5 + 2.3 = 5.2 NET (gross + fee).
A10: Gross activity | B10: network_cost | C10: B | D10: 1.6 | E10: ='Data - Stripe'!H15 -> 0 | F10: =SUMIFS('Data - Internal'!$D$2:$D$91,'Data - Internal'!$A$2:$A$91,F$4,'Data - Internal'!$B$2:$B$91,$B10) -> 0 | G10: =SUMIFS('Data - Internal'!$D$2:$D$91,'Data - Internal'!$A$2:$A$91,G$4,'Data - Internal'!$B$2:$B$91,$B10) -> 0 | H10: =SUMIFS('Data - Internal'!$D$2:$D$91,'Data - Internal'!$A$2:$A$91,H$4,'Data - Internal'!$B$2:$B$91,$B10) -> -138824.01 | I10: =SUMIFS('Data - Internal'!$D$2:$D$91,'Data - Internal'!$A$2:$A$91,I$4,'Data - Internal'!$B$2:$B$91,$B10) -> 0 | J10: =SUMIFS('Data - Internal'!$D$2:$D$91,'Data - Internal'!$A$2:$A$91,J$4,'Data - Internal'!$B$2:$B$91,$B10) -> -3383.29 | K10: =SUMIFS('Data - Internal'!$D$2:$D$91,'Data - Internal'!$A$2:$A$91,K$4,'Data - Internal'!$B$2:$B$91,$B10) -> -2857156.7 | L10: =SUMIFS('Data - Internal'!$D$2:$D$91,'Data - Internal'!$A$2:$A$91,L$4,'Data - Internal'!$B$2:$B$91,$B10) -> -1965.6 | M10: =SUMIFS('Data - Internal'!$D$2:$D$91,'Data - Internal'!$A$2:$A$91,M$4,'Data - Internal'!$B$2:$B$91,$B10) -> -13725550 | ... Q10: =SUMIFS('Data - Internal'!$D$2:$D$91,'Data - Internal'!$A$2:$A$91,Q$4,'Data - Internal'!$B$2:$B$91,$B10) -> 0 | R10: =SUM(F10:Q10) -> -16959837 | S10: =SUMIFS('Data - Stripe'!F:F,'Data - Stripe'!A:A,'Recon - Stripe vs Internal'!B10) -> -16959836 | T10: =R10-S10 -> -0.46 | U10: =IF(ABS(T10)<1,"✓","✗") -> ✓ | V10: =IF(U10="✓","",IF(R10=0,"Not in Internal",IF(S10=0,"Not in Stripe",IF(ABS(T10)<ABS(S10)*0.001,"Rounding",IF(T10>0,"Internal over Stripe","Internal under Stripe")))))
A11: Fees | B11: dispute_fee | C11: I | D11: 2.2 | E11: Stripe fee on disputes (Internal split — Stripe reports in col E of 'dispute' row). | F11: =SUMIFS('Data - Internal'!$D$2:$D$91,'Data - Internal'!$A$2:$A$91,F$4,'Data - Internal'!$B$2:$B$91,$B11) -> -675 | G11: =SUMIFS('Data - Internal'!$D$2:$D$91,'Data - Internal'!$A$2:$A$91,G$4,'Data - Internal'!$B$2:$B$91,$B11) -> 0 | H11: =SUMIFS('Data - Internal'!$D$2:$D$91,'Data - Internal'!$A$2:$A$91,H$4,'Data - Internal'!$B$2:$B$91,$B11) -> -2205 | I11: =SUMIFS('Data - Internal'!$D$2:$D$91,'Data - Internal'!$A$2:$A$91,I$4,'Data - Internal'!$B$2:$B$91,$B11) -> 0 | J11: =SUMIFS('Data - Internal'!$D$2:$D$91,'Data - Internal'!$A$2:$A$91,J$4,'Data - Internal'!$B$2:$B$91,$B11) -> 0 | K11: =SUMIFS('Data - Internal'!$D$2:$D$91,'Data - Internal'!$A$2:$A$91,K$4,'Data - Internal'!$B$2:$B$91,$B11) -> 0 | L11: =SUMIFS('Data - Internal'!$D$2:$D$91,'Data - Internal'!$A$2:$A$91,L$4,'Data - Internal'!$B$2:$B$91,$B11) -> 0 | M11: =SUMIFS('Data - Internal'!$D$2:$D$91,'Data - Internal'!$A$2:$A$91,M$4,'Data - Internal'!$B$2:$B$91,$B11) -> -42345 | ... Q11: =SUMIFS('Data - Internal'!$D$2:$D$91,'Data - Internal'!$A$2:$A$91,Q$4,'Data - Internal'!$B$2:$B$91,$B11) -> 0 | R11: =SUM(F11:Q11) -> -54135 | S11: =SUMIFS('Data - Stripe'!F:F,'Data - Stripe'!A:A,'Recon - Stripe vs Internal'!B11) -> 0 | T11: =R11-S11 -> -54135 | U11: =IF(ABS(T11)<1,"✓","✗") -> ✗ | V11: Bundled in Stripe ref 5.1 (composite) | W11: Internal-only fee split. Component of dispute composite: nets off with ref 1.4 dispute_gross + ref 5.1 dispute (Stripe). 1.4 + 2.2 = 5.1 NET.
A12: Fees | B12: dispute_reversal_fee | C12: I | D12: 2.3 | E12: Stripe fee on dispute reversals (Internal split — Stripe reports in col E of 'dispute_reversal' row). | F12: =SUMIFS('Data - Internal'!$D$2:$D$91,'Data - Internal'!$A$2:$A$91,F$4,'Data - Internal'!$B$2:$B$91,$B12) -> 450 | G12: =SUMIFS('Data - Internal'!$D$2:$D$91,'Data - Internal'!$A$2:$A$91,G$4,'Data - Internal'!$B$2:$B$91,$B12) -> 0 | H12: =SUMIFS('Data - Internal'!$D$2:$D$91,'Data - Internal'!$A$2:$A$91,H$4,'Data - Internal'!$B$2:$B$91,$B12) -> 0 | I12: =SUMIFS('Data - Internal'!$D$2:$D$91,'Data - Internal'!$A$2:$A$91,I$4,'Data - Internal'!$B$2:$B$91,$B12) -> 0 | J12: =SUMIFS('Data - Internal'!$D$2:$D$91,'Data - Internal'!$A$2:$A$91,J$4,'Data - Internal'!$B$2:$B$91,$B12) -> 0 | K12: =SUMIFS('Data - Internal'!$D$2:$D$91,'Data - Internal'!$A$2:$A$91,K$4,'Data - Internal'!$B$2:$B$91,$B12) -> 0 | L12: =SUMIFS('Data - Internal'!$D$2:$D$91,'Data - Internal'!$A$2:$A$91,L$4,'Data - Internal'!$B$2:$B$91,$B12) -> 0 | M12: =SUMIFS('Data - Internal'!$D$2:$D$91,'Data - Internal'!$A$2:$A$91,M$4,'Data - Internal'!$B$2:$B$91,$B12) -> 0 | ... Q12: =SUMIFS('Data - Internal'!$D$2:$D$91,'Data - Internal'!$A$2:$A$91,Q$4,'Data - Internal'!$B$2:$B$91,$B12) -> 0 | R12: =SUM(F12:Q12) -> 450 | S12: =SUMIFS('Data - Stripe'!F:F,'Data - Stripe'!A:A,'Recon - Stripe vs Internal'!B12) -> 0 | T12: =R12-S12 -> 450 | U12: =IF(ABS(T12)<1,"✓","✗") -> ✗ | V12: Bundled in Stripe ref 5.2 (composite) | W12: Internal-only fee split. Component of dispute_reversal composite: nets off with ref 1.5 dispute_reversal_gross + ref 5.2 dispute_reversal (Stripe). 1.5 + 2.3 = 5.2 NET.
A13: Fees | B13: fee | C13: B | D13: 2.5 | E13: ='Data - Stripe'!H14 -> 0 | F13: =SUMIFS('Data - Internal'!$D$2:$D$91,'Data - Internal'!$A$2:$A$91,F$4,'Data - Internal'!$B$2:$B$91,$B13) -> 576119.01 | G13: =SUMIFS('Data - Internal'!$D$2:$D$91,'Data - Internal'!$A$2:$A$91,G$4,'Data - Internal'!$B$2:$B$91,$B13) -> 0 | H13: =SUMIFS('Data - Internal'!$D$2:$D$91,'Data - Internal'!$A$2:$A$91,H$4,'Data - Internal'!$B$2:$B$91,$B13) -> -2378.82 | I13: =SUMIFS('Data - Internal'!$D$2:$D$91,'Data - Internal'!$A$2:$A$91,I$4,'Data - Internal'!$B$2:$B$91,$B13) -> 0 | J13: =SUMIFS('Data - Internal'!$D$2:$D$91,'Data - Internal'!$A$2:$A$91,J$4,'Data - Internal'!$B$2:$B$91,$B13) -> -263.23 | K13: =SUMIFS('Data - Internal'!$D$2:$D$91,'Data - Internal'!$A$2:$A$91,K$4,'Data - Internal'!$B$2:$B$91,$B13) -> -1138670.9 | L13: =SUMIFS('Data - Internal'!$D$2:$D$91,'Data - Internal'!$A$2:$A$91,L$4,'Data - Internal'!$B$2:$B$91,$B13) -> -80.43 | M13: =SUMIFS('Data - Internal'!$D$2:$D$91,'Data - Internal'!$A$2:$A$91,M$4,'Data - Internal'!$B$2:$B$91,$B13) -> -353330.84 | ... Q13: =SUMIFS('Data - Internal'!$D$2:$D$91,'Data - Internal'!$A$2:$A$91,Q$4,'Data - Internal'!$B$2:$B$91,$B13) -> 0 | R13: =SUM(F13:Q13) -> -929361.36 | S13: =SUMIFS('Data - Stripe'!F:F,'Data - Stripe'!A:A,'Recon - Stripe vs Internal'!B13) -> -1505480.4 | T13: =R13-S13 -> 576119.07 | U13: =IF(ABS(T13)<1,"✓","✗") -> ✗ | V13: SIGN ANOMALY (mirror of ref 1.1) | W13: Generic Stripe fee. Internal $-929K vs Stripe NET $-1.51M, Δ +$576,119 = SIGN ANOMALY on billing/fee (see Data-Internal!D7 note). When sign is corrected, Internal fee should equal -$1.51M and tie to Stripe NET. Until corrected, the +$576K Δ is a known reconciling item. Also bundles fee_fee (-$23,884 from ref 2.4).
A14: Cash movements | B14: transfer | C14: B | D14: 3.1 | E14: ='Data - Stripe'!H9 -> 0 | F14: =SUMIFS('Data - Internal'!$D$2:$D$91,'Data - Internal'!$A$2:$A$91,F$4,'Data - Internal'!$B$2:$B$91,$B14) -> -17389232 | G14: =SUMIFS('Data - Internal'!$D$2:$D$91,'Data - Internal'!$A$2:$A$91,G$4,'Data - Internal'!$B$2:$B$91,$B14) -> 0 | H14: =SUMIFS('Data - Internal'!$D$2:$D$91,'Data - Internal'!$A$2:$A$91,H$4,'Data - Internal'!$B$2:$B$91,$B14) -> -8444835.2 | I14: =SUMIFS('Data - Internal'!$D$2:$D$91,'Data - Internal'!$A$2:$A$91,I$4,'Data - Internal'!$B$2:$B$91,$B14) -> -23256.96 | J14: =SUMIFS('Data - Internal'!$D$2:$D$91,'Data - Internal'!$A$2:$A$91,J$4,'Data - Internal'!$B$2:$B$91,$B14) -> 0 | K14: =SUMIFS('Data - Internal'!$D$2:$D$91,'Data - Internal'!$A$2:$A$91,K$4,'Data - Internal'!$B$2:$B$91,$B14) -> 0 | L14: =SUMIFS('Data - Internal'!$D$2:$D$91,'Data - Internal'!$A$2:$A$91,L$4,'Data - Internal'!$B$2:$B$91,$B14) -> 0 | M14: =SUMIFS('Data - Internal'!$D$2:$D$91,'Data - Internal'!$A$2:$A$91,M$4,'Data - Internal'!$B$2:$B$91,$B14) -> -9.1361091e+08 | ... Q14: =SUMIFS('Data - Internal'!$D$2:$D$91,'Data - Internal'!$A$2:$A$91,Q$4,'Data - Internal'!$B$2:$B$91,$B14) -> 0 | R14: =SUM(F14:Q14) -> -9.3946824e+08 | S14: =SUMIFS('Data - Stripe'!F:F,'Data - Stripe'!A:A,'Recon - Stripe vs Internal'!B14) -> -9.3946824e+08 | T14: =R14-S14 -> 0 | U14: =IF(ABS(T14)<1,"✓","✗") -> ✓ | V14: =IF(U14="✓","",IF(R14=0,"Not in Internal",IF(S14=0,"Not in Stripe",IF(ABS(T14)<ABS(S14)*0.001,"Rounding",IF(T14>0,"Internal over Stripe","Internal under Stripe")))))
A15: Cash movements | B15: transfer_reversal | C15: B | D15: 3.2 | E15: ='Data - Stripe'!H10 -> 0 | F15: =SUMIFS('Data - Internal'!$D$2:$D$91,'Data - Internal'!$A$2:$A$91,F$4,'Data - Internal'!$B$2:$B$91,$B15) -> 119440.23 | G15: =SUMIFS('Data - Internal'!$D$2:$D$91,'Data - Internal'!$A$2:$A$91,G$4,'Data - Internal'!$B$2:$B$91,$B15) -> 0 | H15: =SUMIFS('Data - Internal'!$D$2:$D$91,'Data - Internal'!$A$2:$A$91,H$4,'Data - Internal'!$B$2:$B$91,$B15) -> 89879.46 | I15: =SUMIFS('Data - Internal'!$D$2:$D$91,'Data - Internal'!$A$2:$A$91,I$4,'Data - Internal'!$B$2:$B$91,$B15) -> 0 | J15: =SUMIFS('Data - Internal'!$D$2:$D$91,'Data - Internal'!$A$2:$A$91,J$4,'Data - Internal'!$B$2:$B$91,$B15) -> 0 | K15: =SUMIFS('Data - Internal'!$D$2:$D$91,'Data - Internal'!$A$2:$A$91,K$4,'Data - Internal'!$B$2:$B$91,$B15) -> 0 | L15: =SUMIFS('Data - Internal'!$D$2:$D$91,'Data - Internal'!$A$2:$A$91,L$4,'Data - Internal'!$B$2:$B$91,$B15) -> 0 | M15: =SUMIFS('Data - Internal'!$D$2:$D$91,'Data - Internal'!$A$2:$A$91,M$4,'Data - Internal'!$B$2:$B$91,$B15) -> 3990661 | ... Q15: =SUMIFS('Data - Internal'!$D$2:$D$91,'Data - Internal'!$A$2:$A$91,Q$4,'Data - Internal'!$B$2:$B$91,$B15) -> 0 | R15: =SUM(F15:Q15) -> 4199980.7 | S15: =SUMIFS('Data - Stripe'!F:F,'Data - Stripe'!A:A,'Recon - Stripe vs Internal'!B15) -> 4199980.7 | T15: =R15-S15 -> 0 | U15: =IF(ABS(T15)<1,"✓","✗") -> ✓ | V15: =IF(U15="✓","",IF(R15=0,"Not in Internal",IF(S15=0,"Not in Stripe",IF(ABS(T15)<ABS(S15)*0.001,"Rounding",IF(T15>0,"Internal over Stripe","Internal under Stripe")))))
A16: Cash movements | B16: connect_collection_transfer | C16: B | D16: 3.3 | E16: ='Data - Stripe'!H13 -> 0 | F16: =SUMIFS('Data - Internal'!$D$2:$D$91,'Data - Internal'!$A$2:$A$91,F$4,'Data - Internal'!$B$2:$B$91,$B16) -> 0 | G16: =SUMIFS('Data - Internal'!$D$2:$D$91,'Data - Internal'!$A$2:$A$91,G$4,'Data - Internal'!$B$2:$B$91,$B16) -> 0 | H16: =SUMIFS('Data - Internal'!$D$2:$D$91,'Data - Internal'!$A$2:$A$91,H$4,'Data - Internal'!$B$2:$B$91,$B16) -> 0 | I16: =SUMIFS('Data - Internal'!$D$2:$D$91,'Data - Internal'!$A$2:$A$91,I$4,'Data - Internal'!$B$2:$B$91,$B16) -> 0 | J16: =SUMIFS('Data - Internal'!$D$2:$D$91,'Data - Internal'!$A$2:$A$91,J$4,'Data - Internal'!$B$2:$B$91,$B16) -> 0 | K16: =SUMIFS('Data - Internal'!$D$2:$D$91,'Data - Internal'!$A$2:$A$91,K$4,'Data - Internal'!$B$2:$B$91,$B16) -> -526651.5 | L16: =SUMIFS('Data - Internal'!$D$2:$D$91,'Data - Internal'!$A$2:$A$91,L$4,'Data - Internal'!$B$2:$B$91,$B16) -> 0 | M16: =SUMIFS('Data - Internal'!$D$2:$D$91,'Data - Internal'!$A$2:$A$91,M$4,'Data - Internal'!$B$2:$B$91,$B16) -> 0 | ... Q16: =SUMIFS('Data - Internal'!$D$2:$D$91,'Data - Internal'!$A$2:$A$91,Q$4,'Data - Internal'!$B$2:$B$91,$B16) -> 0 | R16: =SUM(F16:Q16) -> -526651.5 | S16: =SUMIFS('Data - Stripe'!F:F,'Data - Stripe'!A:A,'Recon - Stripe vs Internal'!B16) -> -526651.5 | T16: =R16-S16 -> 0 | U16: =IF(ABS(T16)<1,"✓","✗") -> ✓ | V16: =IF(U16="✓","",IF(R16=0,"Not in Internal",IF(S16=0,"Not in Stripe",IF(ABS(T16)<ABS(S16)*0.001,"Rounding",IF(T16>0,"Internal over Stripe","Internal under Stripe")))))
A17: Platform earnings | B17: platform_earning | C17: B | D17: 4.1 | E17: ='Data - Stripe'!H11 -> 0 | F17: =SUMIFS('Data - Internal'!$D$2:$D$91,'Data - Internal'!$A$2:$A$91,F$4,'Data - Internal'!$B$2:$B$91,$B17) -> 1060268.6 | G17: =SUMIFS('Data - Internal'!$D$2:$D$91,'Data - Internal'!$A$2:$A$91,G$4,'Data - Internal'!$B$2:$B$91,$B17) -> 779402.1 | H17: =SUMIFS('Data - Internal'!$D$2:$D$91,'Data - Internal'!$A$2:$A$91,H$4,'Data - Internal'!$B$2:$B$91,$B17) -> 266280.06 | I17: =SUMIFS('Data - Internal'!$D$2:$D$91,'Data - Internal'!$A$2:$A$91,I$4,'Data - Internal'!$B$2:$B$91,$B17) -> 0 | J17: =SUMIFS('Data - Internal'!$D$2:$D$91,'Data - Internal'!$A$2:$A$91,J$4,'Data - Internal'!$B$2:$B$91,$B17) -> 0 | K17: =SUMIFS('Data - Internal'!$D$2:$D$91,'Data - Internal'!$A$2:$A$91,K$4,'Data - Internal'!$B$2:$B$91,$B17) -> 0 | L17: =SUMIFS('Data - Internal'!$D$2:$D$91,'Data - Internal'!$A$2:$A$91,L$4,'Data - Internal'!$B$2:$B$91,$B17) -> 0 | M17: =SUMIFS('Data - Internal'!$D$2:$D$91,'Data - Internal'!$A$2:$A$91,M$4,'Data - Internal'!$B$2:$B$91,$B17) -> 26207053 | ... Q17: =SUMIFS('Data - Internal'!$D$2:$D$91,'Data - Internal'!$A$2:$A$91,Q$4,'Data - Internal'!$B$2:$B$91,$B17) -> 0 | R17: =SUM(F17:Q17) -> 28313004 | S17: =SUMIFS('Data - Stripe'!F:F,'Data - Stripe'!A:A,'Recon - Stripe vs Internal'!B17) -> 28313004 | T17: =R17-S17 -> 0 | U17: =IF(ABS(T17)<1,"✓","✗") -> ✓ | V17: =IF(U17="✓","",IF(R17=0,"Not in Internal",IF(S17=0,"Not in Stripe",IF(ABS(T17)<ABS(S17)*0.001,"Rounding",IF(T17>0,"Internal over Stripe","Internal under Stripe")))))
A18: Platform earnings | B18: platform_earning_refund | C18: B | D18: 4.2 | E18: ='Data - Stripe'!H12 -> 0 | F18: =SUMIFS('Data - Internal'!$D$2:$D$91,'Data - Internal'!$A$2:$A$91,F$4,'Data - Internal'!$B$2:$B$91,$B18) -> -6760.26 | G18: =SUMIFS('Data - Internal'!$D$2:$D$91,'Data - Internal'!$A$2:$A$91,G$4,'Data - Internal'!$B$2:$B$91,$B18) -> -5763.99 | H18: =SUMIFS('Data - Internal'!$D$2:$D$91,'Data - Internal'!$A$2:$A$91,H$4,'Data - Internal'!$B$2:$B$91,$B18) -> -2591.67 | I18: =SUMIFS('Data - Internal'!$D$2:$D$91,'Data - Internal'!$A$2:$A$91,I$4,'Data - Internal'!$B$2:$B$91,$B18) -> 0 | J18: =SUMIFS('Data - Internal'!$D$2:$D$91,'Data - Internal'!$A$2:$A$91,J$4,'Data - Internal'!$B$2:$B$91,$B18) -> 0 | K18: =SUMIFS('Data - Internal'!$D$2:$D$91,'Data - Internal'!$A$2:$A$91,K$4,'Data - Internal'!$B$2:$B$91,$B18) -> 0 | L18: =SUMIFS('Data - Internal'!$D$2:$D$91,'Data - Internal'!$A$2:$A$91,L$4,'Data - Internal'!$B$2:$B$91,$B18) -> 0 | M18: =SUMIFS('Data - Internal'!$D$2:$D$91,'Data - Internal'!$A$2:$A$91,M$4,'Data - Internal'!$B$2:$B$91,$B18) -> -111908.52 | ... Q18: =SUMIFS('Data - Internal'!$D$2:$D$91,'Data - Internal'!$A$2:$A$91,Q$4,'Data - Internal'!$B$2:$B$91,$B18) -> 0 | R18: =SUM(F18:Q18) -> -127024.44 | S18: =SUMIFS('Data - Stripe'!F:F,'Data - Stripe'!A:A,'Recon - Stripe vs Internal'!B18) -> -127024.44 | T18: =R18-S18 -> 0 | U18: =IF(ABS(T18)<1,"✓","✗") -> ✓ | V18: =IF(U18="✓","",IF(R18=0,"Not in Internal",IF(S18=0,"Not in Stripe",IF(ABS(T18)<ABS(S18)*0.001,"Rounding",IF(T18>0,"Internal over Stripe","Internal under Stripe")))))
A19: Platform earnings | B19: revenue_share | C19: B | D19: 4.3 | E19: ='Data - Stripe'!H17 -> 0 | F19: =SUMIFS('Data - Internal'!$D$2:$D$91,'Data - Internal'!$A$2:$A$91,F$4,'Data - Internal'!$B$2:$B$91,$B19) -> 0 | G19: =SUMIFS('Data - Internal'!$D$2:$D$91,'Data - Internal'!$A$2:$A$91,G$4,'Data - Internal'!$B$2:$B$91,$B19) -> 0 | H19: =SUMIFS('Data - Internal'!$D$2:$D$91,'Data - Internal'!$A$2:$A$91,H$4,'Data - Internal'!$B$2:$B$91,$B19) -> 0 | I19: =SUMIFS('Data - Internal'!$D$2:$D$91,'Data - Internal'!$A$2:$A$91,I$4,'Data - Internal'!$B$2:$B$91,$B19) -> 0 | J19: =SUMIFS('Data - Internal'!$D$2:$D$91,'Data - Internal'!$A$2:$A$91,J$4,'Data - Internal'!$B$2:$B$91,$B19) -> 0 | K19: =SUMIFS('Data - Internal'!$D$2:$D$91,'Data - Internal'!$A$2:$A$91,K$4,'Data - Internal'!$B$2:$B$91,$B19) -> 0 | L19: =SUMIFS('Data - Internal'!$D$2:$D$91,'Data - Internal'!$A$2:$A$91,L$4,'Data - Internal'!$B$2:$B$91,$B19) -> 0 | M19: =SUMIFS('Data - Internal'!$D$2:$D$91,'Data - Internal'!$A$2:$A$91,M$4,'Data - Internal'!$B$2:$B$91,$B19) -> 0 | ... Q19: =SUMIFS('Data - Internal'!$D$2:$D$91,'Data - Internal'!$A$2:$A$91,Q$4,'Data - Internal'!$B$2:$B$91,$B19) -> 0 | R19: =SUM(F19:Q19) -> 0 | S19: =SUMIFS('Data - Stripe'!F:F,'Data - Stripe'!A:A,'Recon - Stripe vs Internal'!B19) -> 440487.33 | T19: =R19-S19 -> -440487.33 | U19: =IF(ABS(T19)<1,"✓","✗") -> ✗ | V19: =IF(U19="✓","",IF(R19=0,"Not in Internal",IF(S19=0,"Not in Stripe",IF(ABS(T19)<ABS(S19)*0.001,"Rounding",IF(T19>0,"Internal over Stripe","Internal under Stripe"))))) -> Not in Internal | W19: Stripe-only revenue_share (rebate/incentive credit) of $440,487. Internal does NOT include this in its raw extract — it's missing from the source data. Recon flags as a true reconciling item: either add a manual entry to Internal (other / revenue_share) or accept as a known monthly Stripe-only line. Until added, this represents Stripe income not yet captured in Internal.
A20: Disputes (composite) | B20: dispute | C20: S | D20: 5.1 | E20: ='Data - Stripe'!H7 -> 0 | F20: =SUMIFS('Data - Internal'!$D$2:$D$91,'Data - Internal'!$A$2:$A$91,F$4,'Data - Internal'!$B$2:$B$91,$B20) -> 0 | G20: =SUMIFS('Data - Internal'!$D$2:$D$91,'Data - Internal'!$A$2:$A$91,G$4,'Data - Internal'!$B$2:$B$91,$B20) -> 0 | H20: =SUMIFS('Data - Internal'!$D$2:$D$91,'Data - Internal'!$A$2:$A$91,H$4,'Data - Internal'!$B$2:$B$91,$B20) -> 0 | I20: =SUMIFS('Data - Internal'!$D$2:$D$91,'Data - Internal'!$A$2:$A$91,I$4,'Data - Internal'!$B$2:$B$91,$B20) -> 0 | J20: =SUMIFS('Data - Internal'!$D$2:$D$91,'Data - Internal'!$A$2:$A$91,J$4,'Data - Internal'!$B$2:$B$91,$B20) -> 0 | K20: =SUMIFS('Data - Internal'!$D$2:$D$91,'Data - Internal'!$A$2:$A$91,K$4,'Data - Internal'!$B$2:$B$91,$B20) -> 0 | L20: =SUMIFS('Data - Internal'!$D$2:$D$91,'Data - Internal'!$A$2:$A$91,L$4,'Data - Internal'!$B$2:$B$91,$B20) -> 0 | M20: =SUMIFS('Data - Internal'!$D$2:$D$91,'Data - Internal'!$A$2:$A$91,M$4,'Data - Internal'!$B$2:$B$91,$B20) -> 0 | ... Q20: =SUMIFS('Data - Internal'!$D$2:$D$91,'Data - Internal'!$A$2:$A$91,Q$4,'Data - Internal'!$B$2:$B$91,$B20) -> 0 | R20: =SUM(F20:Q20) -> 0 | S20: =SUMIFS('Data - Stripe'!F:F,'Data - Stripe'!A:A,'Recon - Stripe vs Internal'!B20) -> -657203.1 | T20: =R20-S20 -> 657203.1 | U20: =IF(ABS(T20)<1,"✓","✗") -> ✗ | V20: Split in Internal across refs 1.4 + 2.2 | W20: Stripe-only composite. Nets off with refs 1.4 dispute_gross + 2.2 dispute_fee (Internal splits). 5.1 = 1.4 + 2.2.
A21: Disputes (composite) | B21: dispute_reversal | C21: S | D21: 5.2 | E21: ='Data - Stripe'!H8 -> 0 | F21: =SUMIFS('Data - Internal'!$D$2:$D$91,'Data - Internal'!$A$2:$A$91,F$4,'Data - Internal'!$B$2:$B$91,$B21) -> 0 | G21: =SUMIFS('Data - Internal'!$D$2:$D$91,'Data - Internal'!$A$2:$A$91,G$4,'Data - Internal'!$B$2:$B$91,$B21) -> 0 | H21: =SUMIFS('Data - Internal'!$D$2:$D$91,'Data - Internal'!$A$2:$A$91,H$4,'Data - Internal'!$B$2:$B$91,$B21) -> 0 | I21: =SUMIFS('Data - Internal'!$D$2:$D$91,'Data - Internal'!$A$2:$A$91,I$4,'Data - Internal'!$B$2:$B$91,$B21) -> 0 | J21: =SUMIFS('Data - Internal'!$D$2:$D$91,'Data - Internal'!$A$2:$A$91,J$4,'Data - Internal'!$B$2:$B$91,$B21) -> 0 | K21: =SUMIFS('Data - Internal'!$D$2:$D$91,'Data - Internal'!$A$2:$A$91,K$4,'Data - Internal'!$B$2:$B$91,$B21) -> 0 | L21: =SUMIFS('Data - Internal'!$D$2:$D$91,'Data - Internal'!$A$2:$A$91,L$4,'Data - Internal'!$B$2:$B$91,$B21) -> 0 | M21: =SUMIFS('Data - Internal'!$D$2:$D$91,'Data - Internal'!$A$2:$A$91,M$4,'Data - Internal'!$B$2:$B$91,$B21) -> 0 | ... Q21: =SUMIFS('Data - Internal'!$D$2:$D$91,'Data - Internal'!$A$2:$A$91,Q$4,'Data - Internal'!$B$2:$B$91,$B21) -> 0 | R21: =SUM(F21:Q21) -> 0 | S21: =SUMIFS('Data - Stripe'!F:F,'Data - Stripe'!A:A,'Recon - Stripe vs Internal'!B21) -> 177059.97 | T21: =R21-S21 -> -177059.97 | U21: =IF(ABS(T21)<1,"✓","✗") -> ✗ | V21: Split in Internal across refs 1.5 + 2.3 | W21: Stripe-only composite. Nets off with refs 1.5 dispute_reversal_gross + 2.3 dispute_reversal_fee (Internal splits). 5.2 = 1.5 + 2.3.
A22: Adjustments | B22: other_adjustment | C22: S | D22: 6.1 | E22: ='Data - Stripe'!H16 -> 0 | F22: =SUMIFS('Data - Internal'!$D$2:$D$91,'Data - Internal'!$A$2:$A$91,F$4,'Data - Internal'!$B$2:$B$91,$B22) -> 0 | G22: =SUMIFS('Data - Internal'!$D$2:$D$91,'Data - Internal'!$A$2:$A$91,G$4,'Data - Internal'!$B$2:$B$91,$B22) -> 0 | H22: =SUMIFS('Data - Internal'!$D$2:$D$91,'Data - Internal'!$A$2:$A$91,H$4,'Data - Internal'!$B$2:$B$91,$B22) -> 0 | I22: =SUMIFS('Data - Internal'!$D$2:$D$91,'Data - Internal'!$A$2:$A$91,I$4,'Data - Internal'!$B$2:$B$91,$B22) -> 0 | J22: =SUMIFS('Data - Internal'!$D$2:$D$91,'Data - Internal'!$A$2:$A$91,J$4,'Data - Internal'!$B$2:$B$91,$B22) -> 0 | K22: =SUMIFS('Data - Internal'!$D$2:$D$91,'Data - Internal'!$A$2:$A$91,K$4,'Data - Internal'!$B$2:$B$91,$B22) -> 0 | L22: =SUMIFS('Data - Internal'!$D$2:$D$91,'Data - Internal'!$A$2:$A$91,L$4,'Data - Internal'!$B$2:$B$91,$B22) -> 0 | M22: =SUMIFS('Data - Internal'!$D$2:$D$91,'Data - Internal'!$A$2:$A$91,M$4,'Data - Internal'!$B$2:$B$91,$B22) -> 0 | ... Q22: =SUMIFS('Data - Internal'!$D$2:$D$91,'Data - Internal'!$A$2:$A$91,Q$4,'Data - Internal'!$B$2:$B$91,$B22) -> 0 | R22: =SUM(F22:Q22) -> 0 | S22: =SUMIFS('Data - Stripe'!F:F,'Data - Stripe'!A:A,'Recon - Stripe vs Internal'!B22) -> 25920 | T22: =R22-S22 -> -25920 | U22: =IF(ABS(T22)<1,"✓","✗") -> ✗ | V22: =IF(U22="✓","",IF(R22=0,"Not in Internal",IF(S22=0,"Not in Stripe",IF(ABS(T22)<ABS(S22)*0.001,"Rounding",IF(T22>0,"Internal over Stripe","Internal under Stripe"))))) -> Not in Internal | W22: Stripe-only line. No Internal counterpart. True reconciling item — either add to Internal or accept as small unexplained variance.
A23: Reserve mechanics | B23: payout_minimum_balance_hold | C23: S | D23: 7.1 | E23: ='Data - Stripe'!H18 -> 0 | F23: =SUMIFS('Data - Internal'!$D$2:$D$91,'Data - Internal'!$A$2:$A$91,F$4,'Data - Internal'!$B$2:$B$91,$B23) -> 0 | G23: =SUMIFS('Data - Internal'!$D$2:$D$91,'Data - Internal'!$A$2:$A$91,G$4,'Data - Internal'!$B$2:$B$91,$B23) -> 0 | H23: =SUMIFS('Data - Internal'!$D$2:$D$91,'Data - Internal'!$A$2:$A$91,H$4,'Data - Internal'!$B$2:$B$91,$B23) -> 0 | I23: =SUMIFS('Data - Internal'!$D$2:$D$91,'Data - Internal'!$A$2:$A$91,I$4,'Data - Internal'!$B$2:$B$91,$B23) -> 0 | J23: =SUMIFS('Data - Internal'!$D$2:$D$91,'Data - Internal'!$A$2:$A$91,J$4,'Data - Internal'!$B$2:$B$91,$B23) -> 0 | K23: =SUMIFS('Data - Internal'!$D$2:$D$91,'Data - Internal'!$A$2:$A$91,K$4,'Data - Internal'!$B$2:$B$91,$B23) -> 0 | L23: =SUMIFS('Data - Internal'!$D$2:$D$91,'Data - Internal'!$A$2:$A$91,L$4,'Data - Internal'!$B$2:$B$91,$B23) -> 0 | M23: =SUMIFS('Data - Internal'!$D$2:$D$91,'Data - Internal'!$A$2:$A$91,M$4,'Data - Internal'!$B$2:$B$91,$B23) -> 0 | ... Q23: =SUMIFS('Data - Internal'!$D$2:$D$91,'Data - Internal'!$A$2:$A$91,Q$4,'Data - Internal'!$B$2:$B$91,$B23) -> 0 | R23: =SUM(F23:Q23) -> 0 | S23: =SUMIFS('Data - Stripe'!F:F,'Data - Stripe'!A:A,'Recon - Stripe vs Internal'!B23) -> -5280000 | T23: =R23-S23 -> 5280000 | U23: =IF(ABS(T23)<1,"✓","✗") -> ✗ | V23: =IF(U23="✓","",IF(R23=0,"Not in Internal",IF(S23=0,"Not in Stripe",IF(ABS(T23)<ABS(S23)*0.001,"Rounding",IF(T23>0,"Internal over Stripe","Internal under Stripe"))))) -> Not in Internal | W23: Stripe reserve mechanic (balance-sheet only). Nets off with ref 7.2 release. 7.1 + 7.2 = 0.
A24: Reserve mechanics | B24: payout_minimum_balance_release | C24: S | D24: 7.2 | E24: ='Data - Stripe'!H19 -> 0 | F24: =SUMIFS('Data - Internal'!$D$2:$D$91,'Data - Internal'!$A$2:$A$91,F$4,'Data - Internal'!$B$2:$B$91,$B24) -> 0 | G24: =SUMIFS('Data - Internal'!$D$2:$D$91,'Data - Internal'!$A$2:$A$91,G$4,'Data - Internal'!$B$2:$B$91,$B24) -> 0 | H24: =SUMIFS('Data - Internal'!$D$2:$D$91,'Data - Internal'!$A$2:$A$91,H$4,'Data - Internal'!$B$2:$B$91,$B24) -> 0 | I24: =SUMIFS('Data - Internal'!$D$2:$D$91,'Data - Internal'!$A$2:$A$91,I$4,'Data - Internal'!$B$2:$B$91,$B24) -> 0 | J24: =SUMIFS('Data - Internal'!$D$2:$D$91,'Data - Internal'!$A$2:$A$91,J$4,'Data - Internal'!$B$2:$B$91,$B24) -> 0 | K24: =SUMIFS('Data - Internal'!$D$2:$D$91,'Data - Internal'!$A$2:$A$91,K$4,'Data - Internal'!$B$2:$B$91,$B24) -> 0 | L24: =SUMIFS('Data - Internal'!$D$2:$D$91,'Data - Internal'!$A$2:$A$91,L$4,'Data - Internal'!$B$2:$B$91,$B24) -> 0 | M24: =SUMIFS('Data - Internal'!$D$2:$D$91,'Data - Internal'!$A$2:$A$91,M$4,'Data - Internal'!$B$2:$B$91,$B24) -> 0 | ... Q24: =SUMIFS('Data - Internal'!$D$2:$D$91,'Data - Internal'!$A$2:$A$91,Q$4,'Data - Internal'!$B$2:$B$91,$B24) -> 0 | R24: =SUM(F24:Q24) -> 0 | S24: =SUMIFS('Data - Stripe'!F:F,'Data - Stripe'!A:A,'Recon - Stripe vs Internal'!B24) -> 5280000 | T24: =R24-S24 -> -5280000 | U24: =IF(ABS(T24)<1,"✓","✗") -> ✗ | V24: =IF(U24="✓","",IF(R24=0,"Not in Internal",IF(S24=0,"Not in Stripe",IF(ABS(T24)<ABS(S24)*0.001,"Rounding",IF(T24>0,"Internal over Stripe","Internal under Stripe"))))) -> Not in Internal | W24: Stripe reserve release. Nets off with ref 7.1 hold. 7.1 + 7.2 = 0.
A25: Tax | B25: subscription_tax | C25: I | D25: 8.1 | E25: Subscription sales tax collected (Internal-only category, no Stripe rc counterpart). | F25: =SUMIFS('Data - Internal'!$D$2:$D$91,'Data - Internal'!$A$2:$A$91,F$4,'Data - Internal'!$B$2:$B$91,"silver")+SUMIFS('Data - Internal'!$D$2:$D$91,'Data - Internal'!$A$2:$A$91,F$4,'Data - Internal'!$B$2:$B$91,"diamond")+SUMIFS('Data - Internal'!$D$2:$D$91,'Data - Internal'!$A$2:$A$91,F$4,'Data - Internal'!$B$2:$B$91,"lite")+SUMIFS('Data - Internal'!$D$2:$D$91,'Data - Internal'!$A$2:$A$91,F$4,'Data - Internal'!$B$2:$B$91,"monthly")+SUMIFS('Data - Internal'!$D$2:$D$91,'Data - Internal'!$A$2:$A$91,F$4,'Data - Internal'!$B$2:$B$91,"yearly") -> 0 | G25: =SUMIFS('Data - Internal'!$D$2:$D$91,'Data - Internal'!$A$2:$A$91,G$4,'Data - Internal'!$B$2:$B$91,"silver")+SUMIFS('Data - Internal'!$D$2:$D$91,'Data - Internal'!$A$2:$A$91,G$4,'Data - Internal'!$B$2:$B$91,"diamond")+SUMIFS('Data - Internal'!$D$2:$D$91,'Data - Internal'!$A$2:$A$91,G$4,'Data - Internal'!$B$2:$B$91,"lite")+SUMIFS('Data - Internal'!$D$2:$D$91,'Data - Internal'!$A$2:$A$91,G$4,'Data - Internal'!$B$2:$B$91,"monthly")+SUMIFS('Data - Internal'!$D$2:$D$91,'Data - Internal'!$A$2:$A$91,G$4,'Data - Internal'!$B$2:$B$91,"yearly") -> 0 | H25: =SUMIFS('Data - Internal'!$D$2:$D$91,'Data - Internal'!$A$2:$A$91,H$4,'Data - Internal'!$B$2:$B$91,"silver")+SUMIFS('Data - Internal'!$D$2:$D$91,'Data - Internal'!$A$2:$A$91,H$4,'Data - Internal'!$B$2:$B$91,"diamond")+SUMIFS('Data - Internal'!$D$2:$D$91,'Data - Internal'!$A$2:$A$91,H$4,'Data - Internal'!$B$2:$B$91,"lite")+SUMIFS('Data - Internal'!$D$2:$D$91,'Data - Internal'!$A$2:$A$91,H$4,'Data - Internal'!$B$2:$B$91,"monthly")+SUMIFS('Data - Internal'!$D$2:$D$91,'Data - Internal'!$A$2:$A$91,H$4,'Data - Internal'!$B$2:$B$91,"yearly") -> 0 | I25: =SUMIFS('Data - Internal'!$D$2:$D$91,'Data - Internal'!$A$2:$A$91,I$4,'Data - Internal'!$B$2:$B$91,"silver")+SUMIFS('Data - Internal'!$D$2:$D$91,'Data - Internal'!$A$2:$A$91,I$4,'Data - Internal'!$B$2:$B$91,"diamond")+SUMIFS('Data - Internal'!$D$2:$D$91,'Data - Internal'!$A$2:$A$91,I$4,'Data - Internal'!$B$2:$B$91,"lite")+SUMIFS('Data - Internal'!$D$2:$D$91,'Data - Internal'!$A$2:$A$91,I$4,'Data - Internal'!$B$2:$B$91,"monthly")+SUMIFS('Data - Internal'!$D$2:$D$91,'Data - Internal'!$A$2:$A$91,I$4,'Data - Internal'!$B$2:$B$91,"yearly") -> 0 | J25: =SUMIFS('Data - Internal'!$D$2:$D$91,'Data - Internal'!$A$2:$A$91,J$4,'Data - Internal'!$B$2:$B$91,"silver")+SUMIFS('Data - Internal'!$D$2:$D$91,'Data - Internal'!$A$2:$A$91,J$4,'Data - Internal'!$B$2:$B$91,"diamond")+SUMIFS('Data - Internal'!$D$2:$D$91,'Data - Internal'!$A$2:$A$91,J$4,'Data - Internal'!$B$2:$B$91,"lite")+SUMIFS('Data - Internal'!$D$2:$D$91,'Data - Internal'!$A$2:$A$91,J$4,'Data - Internal'!$B$2:$B$91,"monthly")+SUMIFS('Data - Internal'!$D$2:$D$91,'Data - Internal'!$A$2:$A$91,J$4,'Data - Internal'!$B$2:$B$91,"yearly") -> 0 | K25: =SUMIFS('Data - Internal'!$D$2:$D$91,'Data - Internal'!$A$2:$A$91,K$4,'Data - Internal'!$B$2:$B$91,"silver")+SUMIFS('Data - Internal'!$D$2:$D$91,'Data - Internal'!$A$2:$A$91,K$4,'Data - Internal'!$B$2:$B$91,"diamond")+SUMIFS('Data - Internal'!$D$2:$D$91,'Data - Internal'!$A$2:$A$91,K$4,'Data - Internal'!$B$2:$B$91,"lite")+SUMIFS('Data - Internal'!$D$2:$D$91,'Data - Internal'!$A$2:$A$91,K$4,'Data - Internal'!$B$2:$B$91,"monthly")+SUMIFS('Data - Internal'!$D$2:$D$91,'Data - Internal'!$A$2:$A$91,K$4,'Data - Internal'!$B$2:$B$91,"yearly") -> 0 | L25: =SUMIFS('Data - Internal'!$D$2:$D$91,'Data - Internal'!$A$2:$A$91,L$4,'Data - Internal'!$B$2:$B$91,"silver")+SUMIFS('Data - Internal'!$D$2:$D$91,'Data - Internal'!$A$2:$A$91,L$4,'Data - Internal'!$B$2:$B$91,"diamond")+SUMIFS('Data - Internal'!$D$2:$D$91,'Data - Internal'!$A$2:$A$91,L$4,'Data - Internal'!$B$2:$B$91,"lite")+SUMIFS('Data - Internal'!$D$2:$D$91,'Data - Internal'!$A$2:$A$91,L$4,'Data - Internal'!$B$2:$B$91,"monthly")+SUMIFS('Data - Internal'!$D$2:$D$91,'Data - Internal'!$A$2:$A$91,L$4,'Data - Internal'!$B$2:$B$91,"yearly") -> 0 | M25: =SUMIFS('Data - Internal'!$D$2:$D$91,'Data - Internal'!$A$2:$A$91,M$4,'Data - Internal'!$B$2:$B$91,"silver")+SUMIFS('Data - Internal'!$D$2:$D$91,'Data - Internal'!$A$2:$A$91,M$4,'Data - Internal'!$B$2:$B$91,"diamond")+SUMIFS('Data - Internal'!$D$2:$D$91,'Data - Internal'!$A$2:$A$91,M$4,'Data - Internal'!$B$2:$B$91,"lite")+SUMIFS('Data - Internal'!$D$2:$D$91,'Data - Internal'!$A$2:$A$91,M$4,'Data - Internal'!$B$2:$B$91,"monthly")+SUMIFS('Data - Internal'!$D$2:$D$91,'Data - Internal'!$A$2:$A$91,M$4,'Data - Internal'!$B$2:$B$91,"yearly") -> 0 | ... Q25: =SUMIFS('Data - Internal'!$D$2:$D$91,'Data - Internal'!$A$2:$A$91,Q$4,'Data - Internal'!$B$2:$B$91,"silver")+SUMIFS('Data - Internal'!$D$2:$D$91,'Data - Internal'!$A$2:$A$91,Q$4,'Data - Internal'!$B$2:$B$91,"diamond")+SUMIFS('Data - Internal'!$D$2:$D$91,'Data - Internal'!$A$2:$A$91,Q$4,'Data - Internal'!$B$2:$B$91,"lite")+SUMIFS('Data - Internal'!$D$2:$D$91,'Data - Internal'!$A$2:$A$91,Q$4,'Data - Internal'!$B$2:$B$91,"monthly")+SUMIFS('Data - Internal'!$D$2:$D$91,'Data - Internal'!$A$2:$A$91,Q$4,'Data - Internal'!$B$2:$B$91,"yearly") -> 658522.86 | R25: =SUM(F25:Q25) -> 658522.86 | S25: =SUMIFS('Data - Stripe'!F:F,'Data - Stripe'!A:A,'Recon - Stripe vs Internal'!B25) -> 0 | T25: =R25-S25 -> 658522.86 | U25: =IF(ABS(T25)<1,"✓","✗") -> ✗ | V25: =IF(U25="✓","",IF(R25=0,"Not in Internal",IF(S25=0,"Not in Stripe",IF(ABS(T25)<ABS(S25)*0.001,"Rounding",IF(T25>0,"Internal over Stripe","Internal under Stripe"))))) -> Not in Stripe | W25: Internal-only subscription tax. No Stripe rc counterpart. True reconciling item — booked separately to 2300 sales tax payable; not reflected in Stripe activity since Stripe doesn't categorize tax separately.
A27: TOTAL | F27: =SUM(F5:F25) -> 1618381.2 | G27: =SUM(G5:G25) -> 773638.11 | H27: =SUM(H5:H25) -> 121660.2 | I27: =SUM(I5:I25) -> -23256.96 | J27: =SUM(J5:J25) -> 107945.71 | K27: =SUM(K5:K25) -> -4515176.1 | L27: =SUM(L5:L25) -> 129770.4 | M27: =SUM(M5:M25) -> 11990272 | ... T27: =SUM(T5:T25) -> 1344570.5 | U27: =IF(ABS(T27)<1,"✓","✗") -> ✗
A28: Internal Cat Total (validation) | F28: =SUMIFS('Data - Internal'!$D$2:$D$91,'Data - Internal'!$A$2:$A$91,F$4) -> 1618381.2 | G28: =SUMIFS('Data - Internal'!$D$2:$D$91,'Data - Internal'!$A$2:$A$91,G$4) -> 773638.11 | H28: =SUMIFS('Data - Internal'!$D$2:$D$91,'Data - Internal'!$A$2:$A$91,H$4) -> 121660.2 | I28: =SUMIFS('Data - Internal'!$D$2:$D$91,'Data - Internal'!$A$2:$A$91,I$4) -> -23256.96 | J28: =SUMIFS('Data - Internal'!$D$2:$D$91,'Data - Internal'!$A$2:$A$91,J$4) -> 107945.71 | K28: =SUMIFS('Data - Internal'!$D$2:$D$91,'Data - Internal'!$A$2:$A$91,K$4) -> -4515176.1 | L28: =SUMIFS('Data - Internal'!$D$2:$D$91,'Data - Internal'!$A$2:$A$91,L$4) -> 129770.4 | M28: =SUMIFS('Data - Internal'!$D$2:$D$91,'Data - Internal'!$A$2:$A$91,M$4) -> 11990272 | ... Q28: =SUMIFS('Data - Internal'!$D$2:$D$91,'Data - Internal'!$A$2:$A$91,Q$4) -> 658522.86 | R28: =SUM('Data - Internal'!$D$2:$D$91) -> 24746637 | S28: =SUM('Data - Stripe'!$F$4:$F$19) -> 23402066 | T28: =R28-S28 -> 1344570.5 | U28: =IF(ABS(T28)<1,"✓","✗") -> ✗
A29: Δ (row 29 − row 30) → 0 confirms recon captures all source | F29: =F27-F28 -> 0 | G29: =G27-G28 -> 0 | H29: =H27-H28 -> 3.4924597e-10 | I29: =I27-I28 -> 0 | J29: =J27-J28 -> 0 | K29: =K27-K28 -> 0 | L29: =L27-L28 -> 0 | M29: =M27-M28 -> 1.8626451e-08 | ... T29: =T27-T28 -> 1.2898818e-07 | U29: =IF(ABS(T29)<1,"✓","✗") -> ✓

Sheet Data - Stripe
A1: Stripe Balances
A2: Balance Change from Activity
A3: reporting_category | B3: currency | C3: count | D3: gross | E3: fee | F3: net
A4: charge | B4: usd | C4: 8960268 | D4: 9.5412485e+08 | E4: -576336.36 | F4: 9.5354851e+08
A5: refund | B5: usd | C5: 61947 | D5: -4065765.5 | E5: 0 | F5: -4065765.5
A6: refund_failure | B6: usd | C6: 48 | D6: 7302.96 | E6: 0 | F6: 7302.96
A7: dispute | B7: usd | C7: 3675 | D7: -603068.1 | E7: -54135 | F7: -657203.1
A8: dispute_reversal | B8: usd | C8: 963 | D8: 176609.97 | E8: 450 | F8: 177059.97
A9: transfer | B9: usd | C9: 8586258 | D9: -9.3946824e+08 | E9: 0 | F9: -9.3946824e+08
A10: transfer_reversal | B10: usd | C10: 62466 | D10: 4199980.7 | E10: 0 | F10: 4199980.7
A11: platform_earning | B11: usd | C11: 8810328 | D11: 28313004 | E11: 0 | F11: 28313004
A12: platform_earning_refund | B12: usd | C12: 62805 | D12: -127024.44 | E12: 0 | F12: -127024.44
A13: connect_collection_transfer | B13: usd | C13: 633 | D13: -526651.5 | E13: 0 | F13: -526651.5
A14: fee | B14: usd | C14: 1248 | D14: -1481596.3 | E14: -23884.17 | F14: -1505480.4
A15: network_cost | B15: usd | C15: 1899 | D15: -16959836 | E15: 0 | F15: -16959836
... A21: total | B21: usd | C21: 26552676 | D21: 24055972 | E21: -653905.53 | F21: 7800688.8

Sheet Data - Internal
A1: TRANSACTION_CATEGORY | B1: REPORTING_CATEGORY | C1: Type | D1: 46022
A2: billing | B2: charge | C2: billingcharge | D2: 17389232
A3: billing | B3: dispute_fee | C3: billingdispute_fee | D3: -675
A4: billing | B4: dispute_gross | C4: billingdispute_gross | D4: -73224.81
A5: billing | B5: dispute_reversal_fee | C5: billingdispute_reversal_fee | D5: 450
A6: billing | B6: dispute_reversal_gross | C6: billingdispute_reversal_gross | D6: 54531.63
A7: billing | B7: fee | C7: billingfee | D7: 576119.01
A8: billing | B8: platform_earning | C8: billingplatform_earning | D8: 1060268.6
A9: billing | B9: platform_earning_refund | C9: billingplatform_earning_refund | D9: -6760.26
A10: billing | B10: refund | C10: billingrefund | D10: -111768.15
A11: billing | B11: transfer | C11: billingtransfer | D11: -17389232
A12: billing | B12: transfer_reversal | C12: billingtransfer_reversal | D12: 119440.23
... A91: subscription_tax | B91: yearly | C91: subscription_taxyearly | D91: 4595.46
D92: -
A93: total_subscription | B93: charge | C93: total_subscriptioncharge | D93: 14434388
A94: total_subscription | B94: dispute_fee | C94: total_subscriptiondispute_fee | D94: -8910
A95: total_subscription | B95: dispute_gross | C95: total_subscriptiondispute_gross | D95: -45691.47
A96: total_subscription | B96: dispute_reversal_fee | C96: total_subscriptiondispute_reversal_fee | D96: 0
A97: total_subscription | B97: dispute_reversal_gross | C97: total_subscriptiondispute_reversal_gross | D97: 3108.12
A98: total_subscription | B98: fee | C98: total_subscriptionfee | D98: -10194.24
A99: total_subscription | B99: network_cost | C99: total_subscriptionnetwork_cost | D99: -218854.91
A100: total_subscription | B100: refund | C100: total_subscriptionrefund | D100: -254301.6
D101: -
A102: subscription_cycle_monthly | B102: charge | C102: subscription_cycle_monthlycharge | D102: 13414090
A103: subscription_cycle_monthly | B103: dispute_fee | C103: subscription_cycle_monthlydispute_fee | D103: -8055
A104: subscription_cycle_monthly | B104: dispute_gross | C104: subscription_cycle_monthlydispute_gross | D104: -25219.59
A105: subscription_cycle_monthly | B105: dispute_reversal_fee | C105: subscription_cycle_monthlydispute_reversal_fee | D105: 0
A106: subscription_cycle_monthly | B106: dispute_reversal_gross | C106: subscription_cycle_monthlydispute_reversal_gross | D106: 2244.12
A107: subscription_cycle_monthly | B107: fee | C107: subscription_cycle_monthlyfee | D107: -9943.63
A108: subscription_cycle_monthly | B108: network_cost | C108: subscription_cycle_monthlynetwork_cost | D108: -205120.82
A109: subscription_cycle_monthly | B109: refund | C109: subscription_cycle_monthlyrefund | D109: -48485.64
A110: subscription_cycle_yearly | B110: charge | C110: subscription_cycle_yearlycharge | D110: 1020298.1
A111: subscription_cycle_yearly | B111: dispute_fee | C111: subscription_cycle_yearlydispute_fee | D111: -855
A112: subscription_cycle_yearly | B112: dispute_gross | C112: subscription_cycle_yearlydispute_gross | D112: -20471.88
A113: subscription_cycle_yearly | B113: dispute_reversal_fee | C113: subscription_cycle_yearlydispute_reversal_fee | D113: 0
... A117: subscription_cycle_yearly | B117: refund | C117: subscription_cycle_yearlyrefund | D117: -205815.96
